VizAble/__init__.py
VizAble/app.py
VizAble/chatbot.py
VizAble/check_datatypes.py
VizAble/functions.py
VizAble/generate_plots.py
VizAble/introductions.py
VizAble/rsconnect-python/VizAble.json
VizAble/select_columns.py
VizAble/select_plottypes.py
VizAble/upload_file.py
vizable-0.13.3.dist-info/LICENSE
vizable-0.13.3.dist-info/METADATA
vizable-0.13.3.dist-info/WHEEL
vizable-0.13.3.dist-info/entry_points.txt
vizable-0.13.3.dist-info/RECORD
