Metadata-Version: 2.1
Name: VizAble
Version: 0.13.3
Summary: A web-based data visualization tool that generates accessible visualizations for all users, including people with visual impairments (low vision or blind).
License: MIT
Author: Chi-Ying Chuang
Author-email: rebekah890110@gmail.com
Requires-Python: >=3.9,<4.0
Classifier: License :: OSI Approved :: MIT License
Classifier: Programming Language :: Python :: 3
Classifier: Programming Language :: Python :: 3.9
Classifier: Programming Language :: Python :: 3.10
Classifier: Programming Language :: Python :: 3.11
Classifier: Programming Language :: Python :: 3.12
Requires-Dist: build (>=1.0.3,<2.0.0)
Requires-Dist: cffi (>=1.16.0,<2.0.0)
Requires-Dist: cleo (>=2.1.0,<3.0.0)
Requires-Dist: crashtest (>=0.4.1,<0.5.0)
Requires-Dist: distlib (>=0.3.8,<0.4.0)
Requires-Dist: dulwich (>=0.21.7,<0.22.0)
Requires-Dist: exceptiongroup (>=1.2.0,<2.0.0)
Requires-Dist: google-generativeai (>=0.5.0,<0.6.0)
Requires-Dist: great-tables (>=0.2.0,<0.3.0)
Requires-Dist: ipykernel (>=6.29.1,<7.0.0)
Requires-Dist: jinja2 (>=3.1.3,<4.0.0)
Requires-Dist: matplotlib (>=3.8.4,<4.0.0)
Requires-Dist: numpy (>=1.26.4,<2.0.0)
Requires-Dist: openpyxl (>=3.1.2,<4.0.0)
Requires-Dist: pandas (>=2.2.0,<3.0.0)
Requires-Dist: pickleshare (>=0.7.5,<0.8.0)
Requires-Dist: plotly (>=5.20.0,<6.0.0)
Requires-Dist: poetry (>=1.7.1,<2.0.0)
Requires-Dist: pyarrow (>=15.0.0,<16.0.0)
Requires-Dist: requests (>=2.31.0,<3.0.0)
Requires-Dist: rsconnect-python (>=1.22.0,<2.0.0)
Requires-Dist: seaborn (>=0.13.2,<0.14.0)
Requires-Dist: setuptools (==70.0.0)
Requires-Dist: shiny (>=0.8.0,<0.9.0)
Requires-Dist: shinyswatch (>=0.4.2,<0.5.0)
Requires-Dist: shinywidgets (>=0.3.1,<0.4.0)
Requires-Dist: sphinx (>=7.2.6,<8.0.0)
Requires-Dist: sphinx-press-theme (>=0.8.0,<0.9.0)
Requires-Dist: wheel (>=0.42.0,<0.43.0)
